[
{"train_mad": {"data": 2.8028748793702047, "label": "train_mad", "epoch": 0, "counter": 0}},
{"train_mse": {"data": 35.91351685727185, "label": "train_mse", "epoch": 0, "counter": 0}},
{"train_mape": {"data": 138.18582478891508, "label": "train_mape", "epoch": 0, "counter": 0}},
{"train_msle": {"data": 1.675691051049065, "label": "train_msle", "epoch": 0, "counter": 0}},
{"train_r2": {"data": 0.020442703079475266, "label": "train_r2", "epoch": 0, "counter": 0}},
{"train_kappa": {"data": 0.2564312130553097, "label": "train_kappa", "epoch": 0, "counter": 0}},
{"val_mad": {"data": 2.80271168503342, "label": "val_mad", "epoch": 0, "counter": 0}},
{"val_mse": {"data": 54.6068652320115, "label": "val_mse", "epoch": 0, "counter": 0}},
{"val_mape": {"data": 185.42457042682022, "label": "val_mape", "epoch": 0, "counter": 0}},
{"val_msle": {"data": 1.650194668952538, "label": "val_msle", "epoch": 0, "counter": 0}},
{"val_r2": {"data": 0.11464950289406606, "label": "val_r2", "epoch": 0, "counter": 0}},
{"val_kappa": {"data": 0.4005961422818116, "label": "val_kappa", "epoch": 0, "counter": 0}},
{"train_mad": {"data": 2.6999088513497793, "label": "train_mad", "epoch": 1, "counter": 1}},
{"train_mse": {"data": 33.46698248467611, "label": "train_mse", "epoch": 1, "counter": 1}},
{"train_mape": {"data": 132.08313492135187, "label": "train_mape", "epoch": 1, "counter": 1}},
{"train_msle": {"data": 1.5657974611021463, "label": "train_msle", "epoch": 1, "counter": 1}},
{"train_r2": {"data": 0.08717302654980896, "label": "train_r2", "epoch": 1, "counter": 1}},
{"train_kappa": {"data": 0.30527237020097664, "label": "train_kappa", "epoch": 1, "counter": 1}},
{"val_mad": {"data": 2.850056115973376, "label": "val_mad", "epoch": 1, "counter": 1}},
{"val_mse": {"data": 54.43208196640032, "label": "val_mse", "epoch": 1, "counter": 1}},
{"val_mape": {"data": 191.1731219372729, "label": "val_mape", "epoch": 1, "counter": 1}},
{"val_msle": {"data": 1.6446585251358599, "label": "val_msle", "epoch": 1, "counter": 1}},
{"val_r2": {"data": 0.11748329403804014, "label": "val_r2", "epoch": 1, "counter": 1}},
{"val_kappa": {"data": 0.41209444407799944, "label": "val_kappa", "epoch": 1, "counter": 1}},
{"train_mad": {"data": 2.6689344580898533, "label": "train_mad", "epoch": 2, "counter": 2}},
{"train_mse": {"data": 32.83848263883139, "label": "train_mse", "epoch": 2, "counter": 2}},
{"train_mape": {"data": 129.89998780971288, "label": "train_mape", "epoch": 2, "counter": 2}},
{"train_msle": {"data": 1.5276246648632352, "label": "train_msle", "epoch": 2, "counter": 2}},
{"train_r2": {"data": 0.10431564203236832, "label": "train_r2", "epoch": 2, "counter": 2}},
{"train_kappa": {"data": 0.32101057730126636, "label": "train_kappa", "epoch": 2, "counter": 2}},
{"val_mad": {"data": 3.0070762852999535, "label": "val_mad", "epoch": 2, "counter": 2}},
{"val_mse": {"data": 56.17188681763471, "label": "val_mse", "epoch": 2, "counter": 2}},
{"val_mape": {"data": 205.48706894505938, "label": "val_mape", "epoch": 2, "counter": 2}},
{"val_msle": {"data": 1.6809491910045917, "label": "val_msle", "epoch": 2, "counter": 2}},
{"val_r2": {"data": 0.08927553877937155, "label": "val_r2", "epoch": 2, "counter": 2}},
{"val_kappa": {"data": 0.4196546408086581, "label": "val_kappa", "epoch": 2, "counter": 2}},
{"train_mad": {"data": 2.6455337922467184, "label": "train_mad", "epoch": 3, "counter": 3}},
{"train_mse": {"data": 32.41056663001034, "label": "train_mse", "epoch": 3, "counter": 3}},
{"train_mape": {"data": 128.2491299742421, "label": "train_mape", "epoch": 3, "counter": 3}},
{"train_msle": {"data": 1.4990871936763086, "label": "train_msle", "epoch": 3, "counter": 3}},
{"train_r2": {"data": 0.11598724330092791, "label": "train_r2", "epoch": 3, "counter": 3}},
{"train_kappa": {"data": 0.3338107604350845, "label": "train_kappa", "epoch": 3, "counter": 3}},
{"val_mad": {"data": 3.1013413681059023, "label": "val_mad", "epoch": 3, "counter": 3}},
{"val_mse": {"data": 57.849401935591885, "label": "val_mse", "epoch": 3, "counter": 3}},
{"val_mape": {"data": 206.684222320135, "label": "val_mape", "epoch": 3, "counter": 3}},
{"val_msle": {"data": 1.6778116975729533, "label": "val_msle", "epoch": 3, "counter": 3}},
{"val_r2": {"data": 0.06207769767869864, "label": "val_r2", "epoch": 3, "counter": 3}},
{"val_kappa": {"data": 0.4244676707109388, "label": "val_kappa", "epoch": 3, "counter": 3}},
{"train_mad": {"data": 2.625284053177325, "label": "train_mad", "epoch": 4, "counter": 4}},
{"train_mse": {"data": 32.02196047104963, "label": "train_mse", "epoch": 4, "counter": 4}},
{"train_mape": {"data": 126.9908091563329, "label": "train_mape", "epoch": 4, "counter": 4}},
{"train_msle": {"data": 1.4769065610498535, "label": "train_msle", "epoch": 4, "counter": 4}},
{"train_r2": {"data": 0.12658665076500486, "label": "train_r2", "epoch": 4, "counter": 4}},
{"train_kappa": {"data": 0.34404999524411983, "label": "train_kappa", "epoch": 4, "counter": 4}},
{"val_mad": {"data": 3.104676967377437, "label": "val_mad", "epoch": 4, "counter": 4}},
{"val_mse": {"data": 58.81967049837783, "label": "val_mse", "epoch": 4, "counter": 4}},
{"val_mape": {"data": 202.4492642006383, "label": "val_mape", "epoch": 4, "counter": 4}},
{"val_msle": {"data": 1.6527838790906246, "label": "val_msle", "epoch": 4, "counter": 4}},
{"val_r2": {"data": 0.04634656660682712, "label": "val_r2", "epoch": 4, "counter": 4}},
{"val_kappa": {"data": 0.43163834770190823, "label": "val_kappa", "epoch": 4, "counter": 4}},
{"train_mad": {"data": 2.6049197543076614, "label": "train_mad", "epoch": 5, "counter": 5}},
{"train_mse": {"data": 31.58058371149758, "label": "train_mse", "epoch": 5, "counter": 5}},
{"train_mape": {"data": 125.76240352586932, "label": "train_mape", "epoch": 5, "counter": 5}},
{"train_msle": {"data": 1.4550515577660132, "label": "train_msle", "epoch": 5, "counter": 5}},
{"train_r2": {"data": 0.1386254000534305, "label": "train_r2", "epoch": 5, "counter": 5}},
{"train_kappa": {"data": 0.35450939715397467, "label": "train_kappa", "epoch": 5, "counter": 5}},
{"val_mad": {"data": 3.1767098341466, "label": "val_mad", "epoch": 5, "counter": 5}},
{"val_mse": {"data": 60.7935872345863, "label": "val_mse", "epoch": 5, "counter": 5}},
{"val_mape": {"data": 203.20761767637245, "label": "val_mape", "epoch": 5, "counter": 5}},
{"val_msle": {"data": 1.646295828097706, "label": "val_msle", "epoch": 5, "counter": 5}},
{"val_r2": {"data": 0.0143431150953236, "label": "val_r2", "epoch": 5, "counter": 5}},
{"val_kappa": {"data": 0.4367288007700184, "label": "val_kappa", "epoch": 5, "counter": 5}},
{"train_mad": {"data": 2.5929048943200534, "label": "train_mad", "epoch": 6, "counter": 6}},
{"train_mse": {"data": 31.46261673890873, "label": "train_mse", "epoch": 6, "counter": 6}},
{"train_mape": {"data": 124.89462965616656, "label": "train_mape", "epoch": 6, "counter": 6}},
{"train_msle": {"data": 1.4401773415331336, "label": "train_msle", "epoch": 6, "counter": 6}},
{"train_r2": {"data": 0.14184300219621915, "label": "train_r2", "epoch": 6, "counter": 6}},
{"train_kappa": {"data": 0.36184723405956276, "label": "train_kappa", "epoch": 6, "counter": 6}},
{"val_mad": {"data": 3.1643658852776695, "label": "val_mad", "epoch": 6, "counter": 6}},
{"val_mse": {"data": 60.9653146410552, "label": "val_mse", "epoch": 6, "counter": 6}},
{"val_mape": {"data": 204.0211969383226, "label": "val_mape", "epoch": 6, "counter": 6}},
{"val_msle": {"data": 1.6465725808126574, "label": "val_msle", "epoch": 6, "counter": 6}},
{"val_r2": {"data": 0.011558869121159332, "label": "val_r2", "epoch": 6, "counter": 6}},
{"val_kappa": {"data": 0.43816084593566185, "label": "val_kappa", "epoch": 6, "counter": 6}},
{"train_mad": {"data": 2.577573743817781, "label": "train_mad", "epoch": 7, "counter": 7}},
{"train_mse": {"data": 31.06401000075973, "label": "train_mse", "epoch": 7, "counter": 7}},
{"train_mape": {"data": 124.06123997560337, "label": "train_mape", "epoch": 7, "counter": 7}},
{"train_msle": {"data": 1.4258555269927395, "label": "train_msle", "epoch": 7, "counter": 7}},
{"train_r2": {"data": 0.15271517994776884, "label": "train_r2", "epoch": 7, "counter": 7}},
{"train_kappa": {"data": 0.3691400082555538, "label": "train_kappa", "epoch": 7, "counter": 7}},
{"val_mad": {"data": 3.0881277246291643, "label": "val_mad", "epoch": 7, "counter": 7}},
{"val_mse": {"data": 60.151866532224176, "label": "val_mse", "epoch": 7, "counter": 7}},
{"val_mape": {"data": 195.77186389681543, "label": "val_mape", "epoch": 7, "counter": 7}},
{"val_msle": {"data": 1.6093352740268156, "label": "val_msle", "epoch": 7, "counter": 7}},
{"val_r2": {"data": 0.024747443203621877, "label": "val_r2", "epoch": 7, "counter": 7}},
{"val_kappa": {"data": 0.4418898117102975, "label": "val_kappa", "epoch": 7, "counter": 7}},
{"train_mad": {"data": 2.5683450301538575, "label": "train_mad", "epoch": 8, "counter": 8}},
{"train_mse": {"data": 30.937775516383244, "label": "train_mse", "epoch": 8, "counter": 8}},
{"train_mape": {"data": 123.56557522823695, "label": "train_mape", "epoch": 8, "counter": 8}},
{"train_msle": {"data": 1.4155202496250592, "label": "train_msle", "epoch": 8, "counter": 8}},
{"train_r2": {"data": 0.1561582821865558, "label": "train_r2", "epoch": 8, "counter": 8}},
{"train_kappa": {"data": 0.3742171993952841, "label": "train_kappa", "epoch": 8, "counter": 8}},
{"val_mad": {"data": 3.1567647014950855, "label": "val_mad", "epoch": 8, "counter": 8}},
{"val_mse": {"data": 61.224015443484646, "label": "val_mse", "epoch": 8, "counter": 8}},
{"val_mape": {"data": 198.59344912276626, "label": "val_mape", "epoch": 8, "counter": 8}},
{"val_msle": {"data": 1.6198851094139022, "label": "val_msle", "epoch": 8, "counter": 8}},
{"val_r2": {"data": 0.007364508520903756, "label": "val_r2", "epoch": 8, "counter": 8}},
{"val_kappa": {"data": 0.4419694510207314, "label": "val_kappa", "epoch": 8, "counter": 8}},
{"train_mad": {"data": 2.556746497106792, "label": "train_mad", "epoch": 9, "counter": 9}},
{"train_mse": {"data": 30.595459199587985, "label": "train_mse", "epoch": 9, "counter": 9}},
{"train_mape": {"data": 123.00950644609247, "label": "train_mape", "epoch": 9, "counter": 9}},
{"train_msle": {"data": 1.4064628822458964, "label": "train_msle", "epoch": 9, "counter": 9}},
{"train_r2": {"data": 0.16549511342211498, "label": "train_r2", "epoch": 9, "counter": 9}},
{"train_kappa": {"data": 0.379197568467438, "label": "train_kappa", "epoch": 9, "counter": 9}},
{"val_mad": {"data": 2.932297156617529, "label": "val_mad", "epoch": 9, "counter": 9}},
{"val_mse": {"data": 57.987834862089024, "label": "val_mse", "epoch": 9, "counter": 9}},
{"val_mape": {"data": 180.7821058020912, "label": "val_mape", "epoch": 9, "counter": 9}},
{"val_msle": {"data": 1.5460496233861951, "label": "val_msle", "epoch": 9, "counter": 9}},
{"val_r2": {"data": 0.05983326083418583, "label": "val_r2", "epoch": 9, "counter": 9}},
{"val_kappa": {"data": 0.4479059865616193, "label": "val_kappa", "epoch": 9, "counter": 9}},
{"train_mad": {"data": 2.5450535474870977, "label": "train_mad", "epoch": 10, "counter": 10}},
{"train_mse": {"data": 30.46012780712828, "label": "train_mse", "epoch": 10, "counter": 10}},
{"train_mape": {"data": 122.27936766957271, "label": "train_mape", "epoch": 10, "counter": 10}},
{"train_msle": {"data": 1.3966416610451458, "label": "train_msle", "epoch": 10, "counter": 10}},
{"train_r2": {"data": 0.169186337913249, "label": "train_r2", "epoch": 10, "counter": 10}},
{"train_kappa": {"data": 0.3844175676720196, "label": "train_kappa", "epoch": 10, "counter": 10}},
{"val_mad": {"data": 3.0538751092419316, "label": "val_mad", "epoch": 10, "counter": 10}},
{"val_mse": {"data": 61.15590786516005, "label": "val_mse", "epoch": 10, "counter": 10}},
{"val_mape": {"data": 183.66898607912609, "label": "val_mape", "epoch": 10, "counter": 10}},
{"val_msle": {"data": 1.5603239029939677, "label": "val_msle", "epoch": 10, "counter": 10}},
{"val_r2": {"data": 0.00846874840118561, "label": "val_r2", "epoch": 10, "counter": 10}},
{"val_kappa": {"data": 0.44715073943507877, "label": "val_kappa", "epoch": 10, "counter": 10}},
{"train_mad": {"data": 2.5377308615824177, "label": "train_mad", "epoch": 11, "counter": 11}},
{"train_mse": {"data": 30.364443775765533, "label": "train_mse", "epoch": 11, "counter": 11}},
{"train_mape": {"data": 121.83944958648844, "label": "train_mape", "epoch": 11, "counter": 11}},
{"train_msle": {"data": 1.389345656640259, "label": "train_msle", "epoch": 11, "counter": 11}},
{"train_r2": {"data": 0.17179616282938437, "label": "train_r2", "epoch": 11, "counter": 11}},
{"train_kappa": {"data": 0.38837085024981466, "label": "train_kappa", "epoch": 11, "counter": 11}},
{"val_mad": {"data": 2.926686198065933, "label": "val_mad", "epoch": 11, "counter": 11}},
{"val_mse": {"data": 58.25746114314977, "label": "val_mse", "epoch": 11, "counter": 11}},
{"val_mape": {"data": 179.42397355448736, "label": "val_mape", "epoch": 11, "counter": 11}},
{"val_msle": {"data": 1.5384164245504408, "label": "val_msle", "epoch": 11, "counter": 11}},
{"val_r2": {"data": 0.055461763569955136, "label": "val_r2", "epoch": 11, "counter": 11}},
{"val_kappa": {"data": 0.4474347622089351, "label": "val_kappa", "epoch": 11, "counter": 11}},
{"train_mad": {"data": 2.527988470788515, "label": "train_mad", "epoch": 12, "counter": 12}},
{"train_mse": {"data": 30.20591740427575, "label": "train_mse", "epoch": 12, "counter": 12}},
{"train_mape": {"data": 121.36090136443975, "label": "train_mape", "epoch": 12, "counter": 12}},
{"train_msle": {"data": 1.38096984945923, "label": "train_msle", "epoch": 12, "counter": 12}},
{"train_r2": {"data": 0.17612004078776677, "label": "train_r2", "epoch": 12, "counter": 12}},
{"train_kappa": {"data": 0.3931951397595306, "label": "train_kappa", "epoch": 12, "counter": 12}},
{"val_mad": {"data": 3.035165329610371, "label": "val_mad", "epoch": 12, "counter": 12}},
{"val_mse": {"data": 61.664624624515156, "label": "val_mse", "epoch": 12, "counter": 12}},
{"val_mape": {"data": 177.65832124063573, "label": "val_mape", "epoch": 12, "counter": 12}},
{"val_msle": {"data": 1.5381601374137774, "label": "val_msle", "epoch": 12, "counter": 12}},
{"val_r2": {"data": 0.00022083609441703178, "label": "val_r2", "epoch": 12, "counter": 12}},
{"val_kappa": {"data": 0.45121297171607877, "label": "val_kappa", "epoch": 12, "counter": 12}},
{"train_mad": {"data": 2.522436568568798, "label": "train_mad", "epoch": 13, "counter": 13}},
{"train_mse": {"data": 30.229188808527073, "label": "train_mse", "epoch": 13, "counter": 13}},
{"train_mape": {"data": 120.92303337034262, "label": "train_mape", "epoch": 13, "counter": 13}},
{"train_msle": {"data": 1.3746094169520644, "label": "train_msle", "epoch": 13, "counter": 13}},
{"train_r2": {"data": 0.1754853027882951, "label": "train_r2", "epoch": 13, "counter": 13}},
{"train_kappa": {"data": 0.39620710992984653, "label": "train_kappa", "epoch": 13, "counter": 13}},
{"val_mad": {"data": 2.9455966865377214, "label": "val_mad", "epoch": 13, "counter": 13}},
{"val_mse": {"data": 58.97464888875863, "label": "val_mse", "epoch": 13, "counter": 13}},
{"val_mape": {"data": 178.43555756157429, "label": "val_mape", "epoch": 13, "counter": 13}},
{"val_msle": {"data": 1.5369909835269548, "label": "val_msle", "epoch": 13, "counter": 13}},
{"val_r2": {"data": 0.043833875310937076, "label": "val_r2", "epoch": 13, "counter": 13}},
{"val_kappa": {"data": 0.447816089652892, "label": "val_kappa", "epoch": 13, "counter": 13}},
{"train_mad": {"data": 2.5165694947936985, "label": "train_mad", "epoch": 14, "counter": 14}},
{"train_mse": {"data": 30.082831287932635, "label": "train_mse", "epoch": 14, "counter": 14}},
{"train_mape": {"data": 120.69559966892871, "label": "train_mape", "epoch": 14, "counter": 14}},
{"train_msle": {"data": 1.3700019461512016, "label": "train_msle", "epoch": 14, "counter": 14}},
{"train_r2": {"data": 0.17947726987487267, "label": "train_r2", "epoch": 14, "counter": 14}},
{"train_kappa": {"data": 0.39877779531405344, "label": "train_kappa", "epoch": 14, "counter": 14}},
{"val_mad": {"data": 3.0241048427700314, "label": "val_mad", "epoch": 14, "counter": 14}},
{"val_mse": {"data": 62.49612993729404, "label": "val_mse", "epoch": 14, "counter": 14}},
{"val_mape": {"data": 176.3005363415483, "label": "val_mape", "epoch": 14, "counter": 14}},
{"val_msle": {"data": 1.530809400286794, "label": "val_msle", "epoch": 14, "counter": 14}},
{"val_r2": {"data": -0.013260502541067476, "label": "val_r2", "epoch": 14, "counter": 14}},
{"val_kappa": {"data": 0.44937526705509123, "label": "val_kappa", "epoch": 14, "counter": 14}}
]